{
  "updatedAt": "2026-07-12T23:59:57.053Z",
  "results": [
    {
      "productId": "switch2",
      "productName": "Nintendo Switch 2 (본체 단품)",
      "msrp": 648000,
      "retailer": "닌텐도 공식 스토어",
      "url": "https://store.nintendo.co.kr/beeskb6aakor",
      "checkedAt": "2026-07-12T23:59:10.089Z",
      "price": 648000,
      "priceApproximate": false,
      "priceAtOrBelowMsrp": true,
      "stock": "soldout",
      "error": null
    },
    {
      "productId": "switch2-pokopia",
      "productName": "Nintendo Switch 2 포켓몬 포코피아 에디션",
      "msrp": 718000,
      "retailer": "닌텐도 공식 스토어",
      "url": "https://store.nintendo.co.kr/beeskb6nfkor",
      "checkedAt": "2026-07-12T23:59:17.351Z",
      "price": 718000,
      "priceApproximate": false,
      "priceAtOrBelowMsrp": true,
      "stock": "soldout",
      "error": null
    },
    {
      "productId": "switch2",
      "productName": "Nintendo Switch 2 (본체 단품)",
      "msrp": 648000,
      "retailer": "쿠팡",
      "url": "https://www.coupang.com/vp/products/8825720068",
      "checkedAt": "2026-07-12T23:59:23.814Z",
      "price": null,
      "priceApproximate": false,
      "priceAtOrBelowMsrp": null,
      "stock": "unknown",
      "error": null
    },
    {
      "productId": "switch2-pokopia",
      "productName": "Nintendo Switch 2 포켓몬 포코피아 에디션",
      "msrp": 718000,
      "retailer": "쿠팡",
      "url": "https://www.coupang.com/vp/products/9449804782",
      "checkedAt": "2026-07-12T23:59:28.047Z",
      "price": null,
      "priceApproximate": false,
      "priceAtOrBelowMsrp": null,
      "stock": "unknown",
      "error": null
    },
    {
      "productId": "switch2",
      "productName": "Nintendo Switch 2 (본체 단품)",
      "msrp": 648000,
      "retailer": "11번가",
      "url": "https://www.11st.co.kr/products/8369248443",
      "checkedAt": "2026-07-12T23:59:32.163Z",
      "price": 648000,
      "priceApproximate": false,
      "priceAtOrBelowMsrp": true,
      "stock": "soldout",
      "error": null
    },
    {
      "productId": "switch2-pokopia",
      "productName": "Nintendo Switch 2 포켓몬 포코피아 에디션",
      "msrp": 718000,
      "retailer": "11번가",
      "url": "https://www.11st.co.kr/products/9242538403",
      "checkedAt": "2026-07-12T23:59:41.477Z",
      "price": 847880,
      "priceApproximate": true,
      "priceAtOrBelowMsrp": false,
      "stock": "soldout",
      "error": null
    },
    {
      "productId": "switch2",
      "productName": "Nintendo Switch 2 (본체 단품)",
      "msrp": 648000,
      "retailer": "G마켓",
      "url": "https://item.gmarket.co.kr/Item?goodscode=4448997273",
      "checkedAt": "2026-07-12T23:59:48.337Z",
      "price": null,
      "priceApproximate": false,
      "priceAtOrBelowMsrp": null,
      "stock": "unknown",
      "error": null
    },
    {
      "productId": "switch2",
      "productName": "Nintendo Switch 2 (본체 단품)",
      "msrp": 648000,
      "retailer": "옥션",
      "url": "http://itempage3.auction.co.kr/DetailView.aspx?itemno=E962420166",
      "checkedAt": "2026-07-12T23:59:52.766Z",
      "price": null,
      "priceApproximate": false,
      "priceAtOrBelowMsrp": null,
      "stock": "unknown",
      "error": null
    }
  ]
}
